time.v
`define INCR(var) var <= var + 1
`define DECR(var) var <= var - 1

module pll #(
	parameter [31:0] DIV= 50_000_000  // 50 Mhz
)(
	output reg tick,
	
	input clk, rst_n
);
	localparam CNT_MAX = DIV - 1;
	reg [31:0] counter;
	always @(posedge clk or negedge rst_n) begin
		if (!rst_n) begin 
			counter <= 0;
			tick <= 0;
		end
		else if (counter >= CNT_MAX) begin
			counter <= 0;
			tick <= 1;
		end
		else begin 
			counter <= counter + 1;
			tick <= 0;
		end
	end
endmodule

module TIME_REPORTER(
	output reg	[13:0] 	rtc_year,
	output reg	[3:0] 	rtc_month,
	output reg	[4:0] 	rtc_day, rtc_hour,
	output wire	[2:0] 	rtc_dow,
	output reg	[5:0] 	rtc_minute, rtc_second,

	output reg	alarm_out,
			timer_out,
			error,

	input	clk_50Mhz,
		rst_n,
		wr_en,
		alarm_en,
		timer_en,
	
	input [13:0] data_in,
	input [3:0] addr
	
	);


	/* clk divider */
	
	wire second_tick;

	pll #(.DIV(50_000_000)) pll_inst(
		.clk(clk_50Mhz),
		.rst_n(rst_n),
		.tick(second_tick)
	);
		
	/* register files */

	reg [13:0] alarm_year;
	reg [3:0]  alarm_month;
	reg [4:0] alarm_day;
	reg [4:0] alarm_hour, timer_hour;
	reg [5:0] alarm_minute, timer_minute,
		 alarm_second, timer_second;
	
	/* months */

	localparam	JAN=1,
			FEB=2,
			MAR=3,
			APR=4,
			MAY=5,
			JUN=6,
			JUL=7,
			AUG=8,
			SEP=9,
			OCT=10,
			NOV=11,
			DEC=12;

	/* day of week */

	day_of_week zeller(
		.dow(rtc_dow),

		.year(rtc_year),
		.month(rtc_month),
		.day(rtc_day)
	);

	/* month and day logic */
	reg [4:0] maxday, alarm_maxday;
	
	always @* begin
		case (rtc_month)
			JAN, MAR, MAY, JUL, AUG, OCT, DEC: maxday = 31;
			FEB: begin
				maxday = 28;	
				if ( ((rtc_year[1:0] == 0) && ((rtc_year % 100) != 0)) || (rtc_year % 400) == 0) 
					maxday = 29;
			end
			default: maxday = 30;
		endcase
	end

	always @* begin
		case (alarm_month)
			JAN, MAR, MAY, JUL, AUG, OCT, DEC: alarm_maxday = 31;
			FEB: begin
				alarm_maxday = 28;	
				if ( ((alarm_year[1:0] == 0) && ((alarm_year % 100) != 0)) || (alarm_year % 400) == 0) 
					alarm_maxday = 29;
			end
			default: alarm_maxday = 30;
		endcase
	end

	/* alarm/timer logic */
	always @* begin
		alarm_out = 0;
		timer_out = 0;
		if (alarm_en) begin
			if (
				alarm_year == rtc_year 
				&& alarm_month == rtc_month 
				&& alarm_day == rtc_day 
				&& alarm_hour == rtc_hour 
				&& alarm_minute == rtc_minute 
				&& alarm_second == rtc_second
			) begin
				alarm_out = 1;
			end
		end
		
		if (timer_en) begin
			if ( {timer_hour, timer_minute, timer_second} == 0 ) 
				timer_out = 1;
		end

	end

	/* set rtc/timer/alarm logic */
	reg [13:0] secure_data_in;
	reg invalid_data_flag;
	
	localparam	RTC_Y_ADDR=4'H0,
			RTC_M_ADDR=4'H1,
			RTC_D_ADDR=4'H2,
			RTC_H_ADDR=4'H3,
			RTC_MIN_ADDR=4'H4,
			RTC_SEC_ADDR=4'H5,
			
			ALM_Y_ADDR=4'H6,
			ALM_M_ADDR=4'H7,
			ALM_D_ADDR=4'H8,
			ALM_H_ADDR=4'H9,
			ALM_MIN_ADDR=4'HA,
			ALM_SEC_ADDR=4'HB,

			TMR_H_ADDR=4'HC,
			TMR_MIN_ADDR=4'HD,
			TMR_SEC_ADDR=4'HE;

	always @* begin
		secure_data_in = 0;
		invalid_data_flag = 0;
		if (wr_en) begin
			case (addr)
				RTC_Y_ADDR, ALM_Y_ADDR: begin
					if (data_in <= 9999 && data_in >= 1990)
						secure_data_in = data_in;
					else invalid_data_flag = 1;
				end
				RTC_M_ADDR, ALM_M_ADDR: begin
					if (data_in > 0 && data_in <= 12)
						secure_data_in = data_in;
					else invalid_data_flag = 1;
						
				end
				RTC_D_ADDR, ALM_D_ADDR: begin
					if (data_in > 0 && data_in <= maxday)
						secure_data_in = data_in;
					else invalid_data_flag = 1;
						
				end
				RTC_H_ADDR, ALM_H_ADDR, TMR_H_ADDR: begin
					if (data_in < 24) 
						secure_data_in = data_in;
					else invalid_data_flag = 1;
					
				end
				RTC_MIN_ADDR, ALM_MIN_ADDR, TMR_MIN_ADDR: begin
					if (data_in < 60)
						secure_data_in = data_in;
					else invalid_data_flag = 1;
						
				end
				RTC_SEC_ADDR, ALM_SEC_ADDR, TMR_SEC_ADDR: begin
					if (data_in < 60) 
						secure_data_in = data_in;
					else invalid_data_flag = 1;
						
				end
				default: invalid_data_flag = 1;
			endcase
		end
	end

	/* sequential logic */

	wire rtc_minute_ismax = rtc_second >= 59;
	wire rtc_hour_ismax = (rtc_second >= 59) && (rtc_minute >= 59);
	wire rtc_day_ismax = (rtc_second >= 59) && (rtc_minute >= 59) && (rtc_hour >= 23);
	wire rtc_month_ismax = (rtc_second >= 59) && (rtc_minute >= 59) && (rtc_hour >= 23) && (rtc_day >= maxday); 
	wire rtc_year_ismax = (rtc_second >= 59) && (rtc_minute >= 59) && (rtc_hour >= 23) && (rtc_day >= maxday) && (rtc_month >= 12); 

	always @(posedge clk_50Mhz, negedge rst_n) begin
		if (!rst_n) 
			error <= 0;
		else if (invalid_data_flag)
			error <= 1;
		else error <= 0;
	end

	always @(posedge clk_50Mhz, negedge rst_n) begin
		if (!rst_n) begin
			rtc_year <= 1990;		
			rtc_month <= 1;
			rtc_day <= 1;
			rtc_hour <= 0;
			rtc_minute <= 0;
			rtc_second <= 0;

			alarm_year <= 1990;
			alarm_month <= 1;
			alarm_day <= 1;
			alarm_hour <= 0;
			alarm_minute <= 0;
			alarm_second <= 0;
		end

		else if ( wr_en ) begin
			if ( !invalid_data_flag ) begin
				case (addr)
					4'h0: rtc_year <= secure_data_in[13:0];
					4'h1: rtc_month <= secure_data_in[3:0];
					4'h2: rtc_day <= secure_data_in[4:0];
					4'h3: rtc_hour <= secure_data_in[4:0];
					4'h4: rtc_minute <= secure_data_in[5:0];
					4'h5: rtc_second <= secure_data_in[5:0];

					4'h6: alarm_year <= secure_data_in[13:0];
					4'h7: alarm_month <= secure_data_in[3:0];
					4'h8: alarm_day <= secure_data_in[4:0];
					4'h9: alarm_hour <= secure_data_in[4:0];
					4'ha: alarm_minute <= secure_data_in[5:0];
					4'hb: alarm_second <= secure_data_in[5:0];

					4'hc: timer_hour <= secure_data_in[4:0];
					4'hd: timer_minute <= secure_data_in[5:0];
					4'he: timer_second <= secure_data_in[5:0];
				endcase
			end
		end

		else begin
			if (second_tick) begin
				if (rtc_year_ismax)
					rtc_year <= rtc_year >= 9999 ? 0 : rtc_year + 1;
				if (rtc_month_ismax)
					rtc_month <= rtc_month >= 12 ? 1 : rtc_month + 1;
				if (rtc_day_ismax)
					rtc_day <= (rtc_day >= maxday) ? 1 : rtc_day + 1;
				if (rtc_hour_ismax)
					rtc_hour <= (rtc_hour >= 23) ? 0 : rtc_hour + 1;
				if (rtc_minute_ismax) 
					rtc_minute <= (rtc_minute >= 59) ? 0 : rtc_minute + 1;
				rtc_second <= (rtc_second >= 59) ? 0 : rtc_second + 1;


				if (timer_en) begin
					if (timer_second == 0) begin
						if (timer_minute == 0) begin
							if (timer_hour == 0) 
								timer_second <= 0;
							else begin
								timer_second <= 59;
								timer_minute <= 59;
								`DECR(timer_hour);
							end
						end
						else begin 
							timer_second <= 59;
							`DECR(timer_minute);
						end

					end
					else `DECR(timer_second);
				end

			end
		end
	end
	
endmodule

module day_of_week (
    input  wire [13:0] year,   // 1990..9999
    input  wire [3:0]  month,  // 1..12
    input  wire [4:0]  day,    // 1..31
    output wire [2:0]  dow     // 0=Sun, 1=Mon, ..., 6=Sat
);

    // Adjusted month and year (Jan/Feb treated as months 13/14 of prev year)
    wire [3:0]  m_adj  = (month <= 2) ? month + 12 : month;
    wire [13:0] y_adj  = (month <= 2) ? year - 1   : year;

    // Century and year-within-century
    wire [6:0]  k = y_adj % 100;       // year within century
    wire [6:0]  j = y_adj / 100;       // century

    // Zeller's congruence (all integer arithmetic)
    // h = (day + floor(13*(m+1)/5) + k + floor(k/4) + floor(j/4) + 5*j) mod 7
    wire [19:0] zeller = day
                       + (13 * (m_adj + 1)) / 5
                       + k
                       + (k / 4)
                       + (j / 4)
                       + 5 * j;

    wire [2:0] h = zeller % 7;

    // Remap: Zeller gives 0=Sat,1=Sun; we want 0=Sun..6=Sat
    assign dow = (h + 6) % 7;

endmodule

test/icarus/tb.v
`timescale 1ns/1ps


// ============================================================
//  Testbench for TIME_REPORTER
//  Tool:  iverilog time_tb.v time.v -o sim.out && vvp sim.out
//  View:  gtkwave dump.vcd
// ============================================================

module time_tb;

	localparam CLK_DIV = 100;

    // ----------------------------------------------------------
    // DUT signals
    // ----------------------------------------------------------
    wire [13:0] rtc_year;
    wire [3:0]  rtc_month;
    wire [4:0]  rtc_day, rtc_hour;
    wire [2:0]  rtc_dow;
    wire [5:0]  rtc_minute, rtc_second;
    wire        alarm_out, timer_out, invalid_data_flag;

    reg         clk_50Mhz, rst_n, wr_en, alarm_en, timer_en;
    reg [13:0]  data_in;
    reg [3:0]   addr;

    // ----------------------------------------------------------
    // Instantiate DUT with tiny DIV so 1 "second" = 4 clocks
    // (override the pll parameter through defparam on the
    //  internal instance — works in iverilog)
    // ----------------------------------------------------------
    TIME_REPORTER dut (
        .rtc_year(rtc_year), .rtc_month(rtc_month),
        .rtc_day(rtc_day),   .rtc_hour(rtc_hour),
        .rtc_dow(rtc_dow),
        .rtc_minute(rtc_minute), .rtc_second(rtc_second),
        .alarm_out(alarm_out),   .timer_out(timer_out),
        .error(invalid_data_flag),
        .clk_50Mhz(clk_50Mhz),  .rst_n(rst_n),
        .wr_en(wr_en),           .alarm_en(alarm_en),
        .timer_en(timer_en),
        .data_in(data_in),       .addr(addr)
    );

    // Override PLL divisor so 1 tick = 4 clock edges (fast sim)
    defparam dut.pll_inst.DIV = CLK_DIV;

    // ----------------------------------------------------------
    // Clock: 10ns period = 100 MHz (period doesn't matter,
    //         only DIV count matters for tick generation)
    // ----------------------------------------------------------
    initial clk_50Mhz = 0;
    always #5 clk_50Mhz = ~clk_50Mhz;

    // ----------------------------------------------------------
    // VCD dump for GTKWave
    // ----------------------------------------------------------
    initial begin
        $dumpfile("dump.vcd");
        $dumpvars(0, time_tb);
    end

    // ----------------------------------------------------------
    // Helper task: write one register
    // ----------------------------------------------------------
    task write_reg;
        input [3:0]  a;
        input [13:0] d;
        begin
            @(negedge clk_50Mhz);
            addr    = a;
            data_in = d;
            wr_en   = 1;
            @(negedge clk_50Mhz);
            wr_en   = 0;
        end
    endtask

    // ----------------------------------------------------------
    // Helper task: wait N seconds (N * DIV clock cycles)
    // ----------------------------------------------------------
    task wait_seconds;
        input integer n;
        integer i;
        begin
            for (i = 0; i < n; i = i + 1)
                repeat(CLK_DIV) @(posedge clk_50Mhz);
        end
    endtask

    // ----------------------------------------------------------
    // Helper task: check and print pass/fail
    // ----------------------------------------------------------
    task check;
        input [127:0] test_name; // string passed as bits
        input         condition;
        begin
            if (condition)
                $display("  PASS  %s", test_name);
            else
                $display("  FAIL  %s", test_name);
        end
    endtask

    // ----------------------------------------------------------
    // Main test sequence
    // ----------------------------------------------------------
    integer errors;

    initial begin
        // ---- init ----
        rst_n   = 1; wr_en = 0; alarm_en = 0; timer_en = 0;
        data_in = 0; addr  = 0;
        errors  = 0;

        // ======================================================
        // TEST 1: Reset
        // ======================================================
        $display("\n=== TEST 1: Reset state ===");
        rst_n = 0;
        repeat(4) @(negedge clk_50Mhz);
        rst_n = 1;
        @(negedge clk_50Mhz);

        check("year  resets to 1990", rtc_year   == 14'd1990);
        check("month resets to 1",    rtc_month  == 4'd1);
        check("day   resets to 1",    rtc_day    == 5'd1);
        check("hour  resets to 0",    rtc_hour   == 5'd0);
        check("min   resets to 0",    rtc_minute == 6'd0);
        check("sec   resets to 0",    rtc_second == 6'd0);

        // ======================================================
        // TEST 2: Register writes — set RTC to 2025-06-11 13:45:00
        // ======================================================
        $display("\n=== TEST 2: Register writes ===");

        write_reg(4'h0, 14'd2025);  // year
        write_reg(4'h1, 4'd6);      // month = June
        write_reg(4'h2, 5'd11);     // day = 11
        write_reg(4'h3, 5'd13);     // hour = 13
        write_reg(4'h4, 6'd45);     // minute = 45
        write_reg(4'h5, 6'd0);      // second = 0

        @(negedge clk_50Mhz);
        check("year  = 2025", rtc_year   == 14'd2025);
        check("month = 6",    rtc_month  == 4'd6);
        check("day   = 11",   rtc_day    == 5'd11);
        check("hour  = 13",   rtc_hour   == 5'd13);
        check("min   = 45",   rtc_minute == 6'd45);
        check("sec   = 0",    rtc_second == 6'd0);

        // Check day-of-week: 2025-06-11 is a Wednesday (dow=3)
        check("dow   = 3 (Wed)", rtc_dow == 3'd3);
	$display(" rtc_dow = %d", rtc_dow);

        // ======================================================
        // TEST 3: Invalid data rejection
        // ======================================================
        $display("\n=== TEST 3: Invalid data ===");

        // Bad year (< 1990)
        write_reg(4'h0, 14'd1985);
        check("invalid year rejected",  invalid_data_flag == 1);
        check("year unchanged",         rtc_year == 14'd2025);
        @(negedge clk_50Mhz);

        // Bad month (= 0)
        write_reg(4'h1, 4'd0);
        check("invalid month rejected", invalid_data_flag == 1);
        check("month unchanged",        rtc_month == 4'd6);
        @(negedge clk_50Mhz);

        // Bad hour (>= 24)
        write_reg(4'h3, 14'd24);
        check("invalid hour rejected",  invalid_data_flag == 1);
        check("hour unchanged",         rtc_hour == 5'd13);
        @(negedge clk_50Mhz);

        // Bad minute (>= 60)
        write_reg(4'h4, 14'd60);
        check("invalid minute rejected",invalid_data_flag == 1);
        @(negedge clk_50Mhz);

        // ======================================================
        // TEST 4: Tick / rollover
        // Set time to 23:59:58, wait 3 seconds,
        // expect rollover to next day 00:00:01
        // ======================================================
        $display("\n=== TEST 4: Rollover 23:59:58 -> 00:00:01 ===");

        write_reg(4'h3, 5'd23);
        write_reg(4'h4, 6'd59);
        write_reg(4'h5, 6'd58);

        wait_seconds(3);
        @(negedge clk_50Mhz);

        check("hour  rolled to 0",  rtc_hour   == 5'd0);
        check("min   rolled to 0",  rtc_minute == 6'd0);
        check("sec   = 1",          rtc_second == 6'd1);
        check("day   incremented",  rtc_day    == 5'd12);
	$display("hour: %d, minute=%d, second=%d, day=%d", rtc_hour, rtc_minute, rtc_second, rtc_day);

        // ======================================================
        // TEST 5: Alarm trigger
        // Set RTC to 2025-06-15 08:00:00
        // Set alarm to same time, enable it
        // ======================================================
        $display("\n=== TEST 5: Alarm trigger ===");

        // Set RTC
        write_reg(4'h0, 14'd2025);
        write_reg(4'h1, 4'd6);
        write_reg(4'h2, 5'd15);
        write_reg(4'h3, 5'd8);
        write_reg(4'h4, 6'd0);
        write_reg(4'h5, 6'd0);

        // Set alarm to same datetime
        write_reg(4'h6, 14'd2025);  // alarm year
        write_reg(4'h7, 4'd6);      // alarm month
        write_reg(4'h8, 5'd15);     // alarm day
        write_reg(4'h9, 5'd8);      // alarm hour
        write_reg(4'ha, 6'd0);      // alarm minute
        write_reg(4'hb, 6'd0);      // alarm second

        alarm_en = 1;
        @(negedge clk_50Mhz);
        check("alarm fires at exact match", alarm_out == 1);

        // Advance one second — alarm should be silent
        wait_seconds(1);
        @(negedge clk_50Mhz);
        check("alarm silent after tick", alarm_out == 0);
        alarm_en = 0;

        // ======================================================
        // TEST 6: Timer countdown
        // Load timer = 0h 0m 3s, enable, wait 4 seconds,
        // timer_out should fire at 0
        // ======================================================
        $display("\n=== TEST 6: Timer countdown ===");

        write_reg(4'hc, 5'd0);   // timer_hour  = 0
        write_reg(4'hd, 6'd0);   // timer_minute = 0
        write_reg(4'he, 6'd3);   // timer_second = 3

        timer_en = 1;
        @(negedge clk_50Mhz);
        check("timer not expired yet", timer_out == 0);

        wait_seconds(3);
        @(negedge clk_50Mhz);
        check("timer expired (timer_out=1)", timer_out == 1);

        timer_en = 0;

        // ======================================================
        // DONE
        // ======================================================
        $display("\n=== Simulation complete ===\n");
        #100 $finish;
    end

    // ----------------------------------------------------------
    // Timeout watchdog — kill sim if it hangs
    // ----------------------------------------------------------
    initial begin
        #500_000;
        $display("TIMEOUT — simulation hung");
        $finish;
    end

    // ----------------------------------------------------------
    // Live monitor — prints every second tick
    // ----------------------------------------------------------
    always @(posedge dut.second_tick) begin
        $display("[tick] %04d-%02d-%02d (dow=%0d) %02d:%02d:%02d  | timer=%02d:%02d:%02d",
            rtc_year, rtc_month, rtc_day, rtc_dow,
            rtc_hour, rtc_minute, rtc_second,
            dut.timer_hour, dut.timer_minute, dut.timer_second);
    end

endmodule

test/icarus/dump.vcd
$date
	Thu Jun 11 12:13:59 2026
$end
$version
	Icarus Verilog
$end
$timescale
	1ps
$end
$scope module time_tb $end
$var wire 1 ! timer_out $end
$var wire 14 " rtc_year [13:0] $end
$var wire 6 # rtc_second [5:0] $end
$var wire 4 $ rtc_month [3:0] $end
$var wire 6 % rtc_minute [5:0] $end
$var wire 5 & rtc_hour [4:0] $end
$var wire 3 ' rtc_dow [2:0] $end
$var wire 5 ( rtc_day [4:0] $end
$var wire 1 ) invalid_data_flag $end
$var wire 1 * alarm_out $end
$var parameter 32 + CLK_DIV $end
$var reg 4 , addr [3:0] $end
$var reg 1 - alarm_en $end
$var reg 1 . clk_50Mhz $end
$var reg 14 / data_in [13:0] $end
$var reg 1 0 rst_n $end
$var reg 1 1 timer_en $end
$var reg 1 2 wr_en $end
$var integer 32 3 errors [31:0] $end
$scope module dut $end
$var wire 4 4 addr [3:0] $end
$var wire 1 - alarm_en $end
$var wire 1 . clk_50Mhz $end
$var wire 14 5 data_in [13:0] $end
$var wire 1 0 rst_n $end
$var wire 1 6 rtc_day_ismax $end
$var wire 1 7 rtc_hour_ismax $end
$var wire 1 8 rtc_month_ismax $end
$var wire 1 9 rtc_year_ismax $end
$var wire 1 1 timer_en $end
$var wire 1 2 wr_en $end
$var wire 1 : second_tick $end
$var wire 1 ; rtc_minute_ismax $end
$var wire 3 < rtc_dow [2:0] $end
$var parameter 4 = ALM_D_ADDR $end
$var parameter 4 > ALM_H_ADDR $end
$var parameter 4 ? ALM_MIN_ADDR $end
$var parameter 4 @ ALM_M_ADDR $end
$var parameter 4 A ALM_SEC_ADDR $end
$var parameter 4 B ALM_Y_ADDR $end
$var parameter 32 C APR $end
$var parameter 32 D AUG $end
$var parameter 32 E DEC $end
$var parameter 32 F FEB $end
$var parameter 32 G JAN $end
$var parameter 32 H JUL $end
$var parameter 32 I JUN $end
$var parameter 32 J MAR $end
$var parameter 32 K MAY $end
$var parameter 32 L NOV $end
$var parameter 32 M OCT $end
$var parameter 4 N RTC_D_ADDR $end
$var parameter 4 O RTC_H_ADDR $end
$var parameter 4 P RTC_MIN_ADDR $end
$var parameter 4 Q RTC_M_ADDR $end
$var parameter 4 R RTC_SEC_ADDR $end
$var parameter 4 S RTC_Y_ADDR $end
$var parameter 32 T SEP $end
$var parameter 4 U TMR_H_ADDR $end
$var parameter 4 V TMR_MIN_ADDR $end
$var parameter 4 W TMR_SEC_ADDR $end
$var reg 5 X alarm_day [4:0] $end
$var reg 5 Y alarm_hour [4:0] $end
$var reg 5 Z alarm_maxday [4:0] $end
$var reg 6 [ alarm_minute [5:0] $end
$var reg 4 \ alarm_month [3:0] $end
$var reg 1 * alarm_out $end
$var reg 6 ] alarm_second [5:0] $end
$var reg 14 ^ alarm_year [13:0] $end
$var reg 1 ) error $end
$var reg 1 _ invalid_data_flag $end
$var reg 5 ` maxday [4:0] $end
$var reg 5 a rtc_day [4:0] $end
$var reg 5 b rtc_hour [4:0] $end
$var reg 6 c rtc_minute [5:0] $end
$var reg 4 d rtc_month [3:0] $end
$var reg 6 e rtc_second [5:0] $end
$var reg 14 f rtc_year [13:0] $end
$var reg 14 g secure_data_in [13:0] $end
$var reg 5 h timer_hour [4:0] $end
$var reg 6 i timer_minute [5:0] $end
$var reg 1 ! timer_out $end
$var reg 6 j timer_second [5:0] $end
$scope module pll_inst $end
$var wire 1 . clk $end
$var wire 1 0 rst_n $end
$var parameter 33 k CNT_MAX $end
$var parameter 32 l DIV $end
$var reg 32 m counter [31:0] $end
$var reg 1 : tick $end
$upscope $end
$scope module zeller $end
$var wire 5 n day [4:0] $end
$var wire 4 o month [3:0] $end
$var wire 14 p year [13:0] $end
$var wire 20 q zeller [19:0] $end
$var wire 14 r y_adj [13:0] $end
$var wire 4 s m_adj [3:0] $end
$var wire 7 t k [6:0] $end
$var wire 7 u j [6:0] $end
$var wire 3 v h [2:0] $end
$var wire 3 w dow [2:0] $end
$upscope $end
$upscope $end
$scope task check $end
$var reg 1 x condition $end
$var reg 128 y test_name [127:0] $end
$upscope $end
$scope task wait_seconds $end
$var integer 32 z i [31:0] $end
$var integer 32 { n [31:0] $end
$upscope $end
$scope task write_reg $end
$var reg 4 | a [3:0] $end
$var reg 14 } d [13:0] $end
$upscope $end
$upscope $end
$enddefinitions $end
$comment Show the parameter values. $end
$dumpall
b1100100 l
b1100011 k
b1110 W
b1101 V
b1100 U
b1001 T
b0 S
b101 R
b1 Q
b100 P
b11 O
b10 N
b1010 M
b1011 L
b101 K
b11 J
b110 I
b111 H
b1 G
b10 F
b1100 E
b1000 D
b100 C
b110 B
b1011 A
b111 @
b1010 ?
b1001 >
b1000 =
b1100100 +
$end
#0
$dumpvars
bx }
bx |
bx {
bx z
bx y
xx
b1 w
b10 v
b10011 u
b1011001 t
b1101 s
b11111000101 r
b11110111 q
b11111000110 p
b1 o
b1 n
b0 m
bx j
bx i
bx h
b0 g
b11111000110 f
b0 e
b1 d
b0 c
b0 b
b1 a
b11111 `
0_
b11111000110 ^
b0 ]
b1 \
b0 [
b11111 Z
b0 Y
b1 X
b1 <
0;
0:
09
08
07
06
b0 5
b0 4
b0 3
02
01
00
b0 /
0.
0-
b0 ,
0*
0)
b1 (
b1 '
b0 &
b0 %
b1 $
b0 #
b11111000110 "
0!
$end
#5000
1.
#10000
0.
#15000
1.
#20000
0.
#25000
1.
#30000
0.
#35000
1.
#40000
10
0.
#45000
b1 m
1.
#50000
b11111101001 }
b0 |
1x
b1100101011000110010000000100000001000000111001001100101011100110110010101110100011100110010000001110100011011110010000000110000 y
0.
#55000
b10 m
1.
#60000
b11111101001 g
12
b11111101001 /
b11111101001 5
0.
#65000
b11 '
b11 <
b11 w
b100 v
b10101100 q
b11000 t
b10100 u
b11111101000 r
b11111101001 "
b11111101001 f
b11111101001 p
b11 m
1.
#70000
b0 g
b110 }
b1 |
02
0.
#75000
b100 m
1.
#80000
b110 g
12
b110 /
b110 5
b1 ,
b1 4
0.
#85000
b0 '
b0 <
b0 w
b1 v
b10011011 q
b110 s
b11001 t
b110 g
b11111101001 r
b11110 `
b110 $
b110 d
b110 o
b101 m
1.
#90000
b0 g
b1011 }
b10 |
02
0.
#95000
b110 m
1.
#100000
b1011 g
12
b1011 /
b1011 5
b10 ,
b10 4
0.
#105000
b11 '
b11 <
b11 w
b100 v
b10100101 q
b1011 (
b1011 a
b1011 n
b111 m
1.
#110000
b0 g
b1101 }
b11 |
02
0.
#115000
b1000 m
1.
#120000
b1101 g
12
b1101 /
b1101 5
b11 ,
b11 4
0.
#125000
b1101 &
b1101 b
b1001 m
1.
#130000
b0 g
b101101 }
b100 |
02
0.
#135000
b1010 m
1.
#140000
b101101 g
12
b101101 /
b101101 5
b100 ,
b100 4
0.
#145000
b101101 %
b101101 c
b1011 m
1.
#150000
b0 g
b0 }
b101 |
02
0.
#155000
b1100 m
1.
#160000
12
b0 /
b0 5
b101 ,
b101 4
0.
#165000
b1101 m
1.
#170000
02
0.
#175000
b1110 m
1.
#180000
b11111000001 }
b0 |
b11001000110111101110111001000000010000000100000001111010010000000110011001000000010100001010111011001010110010000101001 y
0.
#185000
b1111 m
1.
#190000
1_
12
b11111000001 /
b11111000001 5
b0 ,
b0 4
0.
#195000
b10000 m
1)
1.
#200000
0_
b111100101100101011000010111001000100000011101010110111001100011011010000110000101101110011001110110010101100100 y
02
0.
#205000
0)
b10001 m
1.
#210000
b0 }
b1 |
0.
#215000
b10010 m
1.
#220000
1_
12
b0 /
b0 5
b1 ,
b1 4
0.
#225000
1)
b10011 m
1.
#230000
0_
b11011010110111101101110011101000110100000100000011101010110111001100011011010000110000101101110011001110110010101100100 y
02
0.
#235000
b10100 m
0)
1.
#240000
b11000 }
b11 |
0.
#245000
b10101 m
1.
#250000
1_
12
b11000 /
b11000 5
b11 ,
b11 4
0.
#255000
b10110 m
1)
1.
#260000
0_
b110100001101111011101010111001000100000011101010110111001100011011010000110000101101110011001110110010101100100 y
02
0.
#265000
0)
b10111 m
1.
#270000
b111100 }
b100 |
0.
#275000
b11000 m
1.
#280000
1_
12
b111100 /
b111100 5
b100 ,
b100 4
0.
#285000
1)
b11001 m
1.
#290000
0_
b100000011011010110100101101110011101010111010001100101001000000111001001100101011010100110010101100011011101000110010101100100 y
02
0.
#295000
b11010 m
0)
1.
#300000
b10111 }
b11 |
0.
#305000
b11011 m
1.
#310000
b10111 g
12
b10111 /
b10111 5
b11 ,
b11 4
0.
#315000
b11100 m
b10111 &
b10111 b
1.
#320000
b0 g
b111011 }
b100 |
02
0.
#325000
b11101 m
1.
#330000
b111011 g
12
b111011 /
b111011 5
b100 ,
b100 4
0.
#335000
b11110 m
b111011 %
b111011 c
1.
#340000
b0 g
b111010 }
b101 |
02
0.
#345000
b11111 m
1.
#350000
b111010 g
12
b111010 /
b111010 5
b101 ,
b101 4
0.
#355000
b100000 m
b111010 #
b111010 e
1.
#360000
b0 g
b0 z
b11 {
02
0.
#365000
b100001 m
1.
#370000
0.
#375000
b100010 m
1.
#380000
0.
#385000
b100011 m
1.
#390000
0.
#395000
b100100 m
1.
#400000
0.
#405000
b100101 m
1.
#410000
0.
#415000
b100110 m
1.
#420000
0.
#425000
b100111 m
1.
#430000
0.
#435000
b101000 m
1.
#440000
0.
#445000
b101001 m
1.
#450000
0.
#455000
b101010 m
1.
#460000
0.
#465000
b101011 m
1.
#470000
0.
#475000
b101100 m
1.
#480000
0.
#485000
b101101 m
1.
#490000
0.
#495000
b101110 m
1.
#500000
0.
#505000
b101111 m
1.
#510000
0.
#515000
b110000 m
1.
#520000
0.
#525000
b110001 m
1.
#530000
0.
#535000
b110010 m
1.
#540000
0.
#545000
b110011 m
1.
#550000
0.
#555000
b110100 m
1.
#560000
0.
#565000
b110101 m
1.
#570000
0.
#575000
b110110 m
1.
#580000
0.
#585000
b110111 m
1.
#590000
0.
#595000
b111000 m
1.
#600000
0.
#605000
b111001 m
1.
#610000
0.
#615000
b111010 m
1.
#620000
0.
#625000
b111011 m
1.
#630000
0.
#635000
b111100 m
1.
#640000
0.
#645000
b111101 m
1.
#650000
0.
#655000
b111110 m
1.
#660000
0.
#665000
b111111 m
1.
#670000
0.
#675000
b1000000 m
1.
#680000
0.
#685000
b1000001 m
1.
#690000
0.
#695000
b1000010 m
1.
#700000
0.
#705000
b1000011 m
1.
#710000
0.
#715000
b1000100 m
1.
#720000
0.
#725000
b1000101 m
1.
#730000
0.
#735000
b1000110 m
1.
#740000
0.
#745000
b1000111 m
1.
#750000
0.
#755000
b1001000 m
1.
#760000
0.
#765000
b1001001 m
1.
#770000
0.
#775000
b1001010 m
1.
#780000
0.
#785000
b1001011 m
1.
#790000
0.
#795000
b1001100 m
1.
#800000
0.
#805000
b1001101 m
1.
#810000
0.
#815000
b1001110 m
1.
#820000
0.
#825000
b1001111 m
1.
#830000
0.
#835000
b1010000 m
1.
#840000
0.
#845000
b1010001 m
1.
#850000
0.
#855000
b1010010 m
1.
#860000
0.
#865000
b1010011 m
1.
#870000
0.
#875000
b1010100 m
1.
#880000
0.
#885000
b1010101 m
1.
#890000
0.
#895000
b1010110 m
1.
#900000
0.
#905000
b1010111 m
1.
#910000
0.
#915000
b1011000 m
1.
#920000
0.
#925000
b1011001 m
1.
#930000
0.
#935000
b1011010 m
1.
#940000
0.
#945000
b1011011 m
1.
#950000
0.
#955000
b1011100 m
1.
#960000
0.
#965000
b1011101 m
1.
#970000
0.
#975000
b1011110 m
1.
#980000
0.
#985000
b1011111 m
1.
#990000
0.
#995000
b1100000 m
1.
#1000000
0.
#1005000
b1100001 m
1.
#1010000
0.
#1015000
b1100010 m
1.
#1020000
0.
#1025000
b1100011 m
1.
#1030000
0.
#1035000
1:
b0 m
1.
#1040000
0.
#1045000
16
17
1;
b111011 #
b111011 e
0:
b1 m
1.
#1050000
0.
#1055000
b10 m
1.
#1060000
0.
#1065000
b11 m
1.
#1070000
0.
#1075000
b100 m
1.
#1080000
0.
#1085000
b101 m
1.
#1090000
0.
#1095000
b110 m
1.
#1100000
0.
#1105000
b111 m
1.
#1110000
0.
#1115000
b1000 m
1.
#1120000
0.
#1125000
b1001 m
1.
#1130000
0.
#1135000
b1010 m
1.
#1140000
0.
#1145000
b1011 m
1.
#1150000
0.
#1155000
b1100 m
1.
#1160000
0.
#1165000
b1101 m
1.
#1170000
0.
#1175000
b1110 m
1.
#1180000
0.
#1185000
b1111 m
1.
#1190000
0.
#1195000
b10000 m
1.
#1200000
0.
#1205000
b10001 m
1.
#1210000
0.
#1215000
b10010 m
1.
#1220000
0.
#1225000
b10011 m
1.
#1230000
0.
#1235000
b10100 m
1.
#1240000
0.
#1245000
b10101 m
1.
#1250000
0.
#1255000
b10110 m
1.
#1260000
0.
#1265000
b10111 m
1.
#1270000
0.
#1275000
b11000 m
1.
#1280000
0.
#1285000
b11001 m
1.
#1290000
0.
#1295000
b11010 m
1.
#1300000
0.
#1305000
b11011 m
1.
#1310000
0.
#1315000
b11100 m
1.
#1320000
0.
#1325000
b11101 m
1.
#1330000
0.
